rtv_solver/__init__.py
rtv_solver/main.py
rtv_solver/offline_rtv_solver.py
rtv_solver/online_rtv_simulator.py
rtv_solver/online_rtv_solver copy.py
rtv_solver/online_rtv_solver.py
rtv_solver/handlers/__init__.py
rtv_solver/handlers/network_handler.py
rtv_solver/handlers/output_handler.py
rtv_solver/handlers/payload_parser.py
rtv_solver/handlers/request_handler.py
rtv_solver/handlers/swap_handler.py
rtv_solver/handlers/trip_handler.py
rtv_solver/handlers/vehicle_handler.py
rtv_solver/structure/__init__.py
rtv_solver/structure/node.py
rtv_solver/structure/payload.py
rtv_solver/structure/request.py
rtv_solver/structure/shared_trip.py
rtv_solver/structure/trip.py
rtv_solver/structure/trip_cost.py
rtv_solver/structure/vehicle.py
rtv_solver/structure/vehicle_stop.py
rtv_solver-0.1.40.dist-info/METADATA
rtv_solver-0.1.40.dist-info/WHEEL
rtv_solver-0.1.40.dist-info/top_level.txt
rtv_solver-0.1.40.dist-info/RECORD
