Metadata-Version: 2.4
Name: rtv_solver
Version: 0.1.40
Summary: A solver for real-time vehicle routing problems
Author: Danushka Edirimanna
Author-email: ke233@cornell.edu
License: MIT
Classifier: Programming Language :: Python :: 3
Classifier: License :: OSI Approved :: MIT License
Classifier: Operating System :: OS Independent
Requires-Python: >=3.10
Requires-Dist: pandas>=1.5.3
Requires-Dist: numpy>=1.26.0
Requires-Dist: requests>=2.31.0
Requires-Dist: gurobipy>=10.0.3
Dynamic: author
Dynamic: author-email
Dynamic: classifier
Dynamic: description
Dynamic: description-content-type
Dynamic: license
Dynamic: requires-dist
Dynamic: requires-python
Dynamic: summary
